{"name":"Stymphalidies","traits":"Uncommon","tags":[],"level":9,"specials":[{"id":"_1kve6n1v2qa","name":"Feather Razor","traits":"","range":"","actions":"one","type":"offense","description":"A stymphalidies’s metallic feathers are razor-sharp and it can beat its wings, flinging feathered shards at its prey. The stymphalidies makes two feather razor Strikes at a single creature, increasing its multiple attack penalty only once after both attacks are made."},{"id":"_9l2668rgdi","name":"Glare","traits":"light, visual","range":"","actions":"two","type":"offense","description":"Requirements The stymphalidies must be in an area of bright light; Effect The stymphalidies ruffles its metallic feathers, blinding all creatures within 30 feet (DC 28 Fortitude save).\nCritical Success The target is unaffected.\nSuccess The target is dazzled for 1 round.\nFailure The target is blinded for 1 round and dazzled for 1 minute.\nCritical Failure The target is blinded for 1 minute."}],"morespells":[],"alignment":"n","size":"large","type":"beast","adjust":0,"description":"","items":"","spellattack":{"value":"","benchmark":"moderate","note":""},"spelldc":{"value":"","benchmark":"moderate","note":""},"savenote":"","creature":"","speed":"10 ft., fly 60 ft.","imgurl":"","spelltype":"","focuspoints":0,"cantriplevel":"","ritualtype":"","rituals":"","spells":["","","","","","","","","","",""],"constant":"","minprof":{"value":"","benchmark":"moderate","note":""},"strength":{"value":"+6","benchmark":"high","note":""},"dexterity":{"value":"+3","benchmark":"low","note":""},"constitution":{"value":"5","benchmark":"moderate","note":""},"intelligence":{"value":"-4","benchmark":"abysmal","note":""},"wisdom":{"value":"+3","benchmark":"low","note":""},"charisma":{"value":"+4","benchmark":"moderate","note":""},"perception":{"value":"16","benchmark":"moderate","note":"low-light Vision"},"acrobatics":{"value":"16","benchmark":"moderate","note":""},"arcana":{"value":"","benchmark":"moderate","note":""},"athletics":{"value":"17","benchmark":"moderate","note":""},"crafting":{"value":"","benchmark":"moderate","note":""},"deception":{"value":"","benchmark":"moderate","note":""},"diplomacy":{"value":"","benchmark":"moderate","note":""},"intimidation":{"value":"","benchmark":"moderate","note":""},"medicine":{"value":"","benchmark":"moderate","note":""},"nature":{"value":"","benchmark":"moderate","note":""},"occultism":{"value":"","benchmark":"moderate","note":""},"performance":{"value":"","benchmark":"moderate","note":""},"religion":{"value":"","benchmark":"moderate","note":""},"society":{"value":"","benchmark":"moderate","note":""},"stealth":{"value":"","benchmark":"moderate","note":""},"survival":{"value":"","benchmark":"moderate","note":""},"thievery":{"value":"","benchmark":"moderate","note":""},"lore":{"value":"","benchmark":"moderate","note":"","name":"lore"},"lorealt":{"value":"","benchmark":"moderate","note":"","name":"lore"},"ac":{"value":"26","benchmark":"moderate","note":""},"hp":{"value":"140","benchmark":"moderate","note":""},"fortitude":{"value":"22","benchmark":"high","note":""},"reflex":{"value":"18","benchmark":"moderate","note":""},"will":{"value":"14","benchmark":"low","note":""},"resistance":{"value":"physical 10 (except adamantium)","benchmark":"moderate","note":""},"weakness":{"value":"sonic 10","benchmark":"moderate","note":""},"immunity":{"value":"fire","benchmark":"moderate","note":""},"roadmap":"","info":"Converted by VaranSL","strikes":[{"id":"_1yeej72noif","name":"beak","traits":"deadly d10","attack":"+23 [+18/+13]","damage":"2d8+11 piercing","type":"Melee"},{"id":"_1tuoatsonrr","name":"wing razor","traits":"agile","attack":"+23 [+19/+15]","damage":"2d4+11 slashing plus 1d4 persistent bleed","type":"Melee"},{"id":"_2245lpqzn48","name":"feather razor","traits":"agile, range increment 30 feet, reload 0","attack":"+20 [+16/+12]","damage":"2d4+6 slashing plus 1d4 persistent bleed","type":"Ranged"}]}